{
  "setting": {},
  "condition": {
    "plugin": {
      "list": []
    },
    "game": {
      "list": []
    },
    "gamePlugin": {
      "list": []
    },
    "miniprogram": {
      "list": [
        {
          "name": "pages/me/me",
          "pathName": "pages/me/me",
          "query": "",
          "scene": null
        },
        {
          "name": "pages/cart/cart",
          "pathName": "pages/cart/cart",
          "query": "",
          "scene": null
        },
        {
          "name": "components/myVideo/myVideo",
          "pathName": "components/myVideo/myVideo",
          "query": "",
          "scene": null
        },
        {
          "name": "pages/map/map",
          "pathName": "pages/map/map",
          "query": "",
          "scene": null
        },
        {
          "name": "pages/details/details",
          "pathName": "pages/details/details",
          "query": "",
          "scene": null
        },
        {
          "name": "pages/strategy/strategy",
          "pathName": "pages/strategy/strategy",
          "query": "",
          "scene": null
        },
        {
          "name": "pages/start/start",
          "pathName": "pages/start/start",
          "query": "",
          "scene": null
        },
        {
          "name": "pages/index/index",
          "pathName": "pages/index/index",
          "query": "",
          "scene": null
        }
      ]
    }
  }
}